Metadata-Version: 1.2
Name: basic-vector3d-package
Version: 1.0.1
Summary: this is a test package with respect to basic calc for vector 3d
Home-page: https:www.iCuriosity.com
Author: iCur
Author-email: moon_8295@163.com
License: UNKNOWN
Platform: UNKNOWN
Requires-Python: >=3.6
